{
    "msg": "Found all projects Successfully",
    "response": [
        {
            "_id": "59bb8b668550940bf4b5e6d8",
            "User_id": "59bb8a296685ac2124a62360",
            "Name": "Ashok",
            "Email": "ashok@betabulls.com",
            "Phone": 8099899823,
            "Address": "Nellore",
            "City": "Nellore",
            "State": "Ap",
            "ZipCode": 524321,
            "ProjectName": "lollypop",
            "OrganizationName": "PAR",
            "PropertyAddress": "Nellore",
            "MetroArea": "Hyd",
            "ConstructionType": "New",
            "PurchasePrice": 25000,
            "SquareFootage": 452,
            "RenovationLevel": "high",
            "Studios": "studio",
            "One_BedRoom_11": 1,
            "Two_BedRoom_12": 2,
            "Three_BedRoom_13": 3,
            "Four_BedRoom_14": 5,
            "__v": 0,
            "createdDate": "2017-09-15T08:12:22.597Z"
        },
        {
            "_id": "59bb8b948550940bf4b5e6d9",
            "User_id": "59bb8a296685ac2124a62360",
            "Name": "BetaBulls",
            "Email": "betaBulls@betabulls.com",
            "Phone": 8099899823,
            "Address": "Nellore",
            "City": "Nellore",
            "State": "Ap",
            "ZipCode": 524321,
            "ProjectName": "lollypop",
            "OrganizationName": "PAR",
            "PropertyAddress": "Nellore",
            "MetroArea": "Hyd",
            "ConstructionType": "New",
            "PurchasePrice": 25000,
            "SquareFootage": 452,
            "RenovationLevel": "high",
            "Studios": "studio",
            "One_BedRoom_11": 1,
            "Two_BedRoom_12": 2,
            "Three_BedRoom_13": 3,
            "Four_BedRoom_14": 5,
            "__v": 0,
            "createdDate": "2017-09-15T08:13:08.866Z"
        },
        {
            "_id": "59bb8b9d8550940bf4b5e6da",
            "User_id": "59bb8a296685ac2124a62360",
            "Name": "BetaBulls01",
            "Email": "betaBulls01@betabulls.com",
            "Phone": 8099899823,
            "Address": "Nellore",
            "City": "Nellore",
            "State": "Ap",
            "ZipCode": 524321,
            "ProjectName": "lollypop",
            "OrganizationName": "PAR",
            "PropertyAddress": "Nellore",
            "MetroArea": "Hyd",
            "ConstructionType": "New",
            "PurchasePrice": 25000,
            "SquareFootage": 452,
            "RenovationLevel": "high",
            "Studios": "studio",
            "One_BedRoom_11": 1,
            "Two_BedRoom_12": 2,
            "Three_BedRoom_13": 3,
            "Four_BedRoom_14": 5,
            "__v": 0,
            "createdDate": "2017-09-15T08:13:17.238Z"
        },
        {
            "_id": "59bb8ba68550940bf4b5e6db",
            "User_id": "59bb8a296685ac2124a62360",
            "Name": "BetaBulls02",
            "Email": "betaBulls02@betabulls.com",
            "Phone": 8099899823,
            "Address": "Nellore",
            "City": "Nellore",
            "State": "Ap",
            "ZipCode": 524321,
            "ProjectName": "lollypop",
            "OrganizationName": "PAR",
            "PropertyAddress": "Nellore",
            "MetroArea": "Hyd",
            "ConstructionType": "New",
            "PurchasePrice": 25000,
            "SquareFootage": 452,
            "RenovationLevel": "high",
            "Studios": "studio",
            "One_BedRoom_11": 1,
            "Two_BedRoom_12": 2,
            "Three_BedRoom_13": 3,
            "Four_BedRoom_14": 5,
            "__v": 0,
            "createdDate": "2017-09-15T08:13:26.855Z"
        },
        {
            "_id": "59bb8bad8550940bf4b5e6dc",
            "User_id": "59bb8a296685ac2124a62360",
            "Name": "BetaBulls03",
            "Email": "betaBulls03@betabulls.com",
            "Phone": 8099899823,
            "Address": "Nellore",
            "City": "Nellore",
            "State": "Ap",
            "ZipCode": 524321,
            "ProjectName": "lollypop",
            "OrganizationName": "PAR",
            "PropertyAddress": "Nellore",
            "MetroArea": "Hyd",
            "ConstructionType": "New",
            "PurchasePrice": 25000,
            "SquareFootage": 452,
            "RenovationLevel": "high",
            "Studios": "studio",
            "One_BedRoom_11": 1,
            "Two_BedRoom_12": 2,
            "Three_BedRoom_13": 3,
            "Four_BedRoom_14": 5,
            "__v": 0,
            "createdDate": "2017-09-15T08:13:33.456Z"
        }
    ]
}
